brocc_li/__about__.py
brocc_li/__init__.py
brocc_li/app.py
brocc_li/entry_points.py
brocc_li-0.0.3.dist-info/METADATA
brocc_li-0.0.3.dist-info/WHEEL
brocc_li-0.0.3.dist-info/entry_points.txt
brocc_li-0.0.3.dist-info/licenses/LICENSE.txt
brocc_li-0.0.3.dist-info/RECORD
