Metadata-Version: 2.4
Name: brocc-li
Version: 0.0.3
Project-URL: Documentation, https://brocc.li
Project-URL: Issues, https://github.com/SubstrateLabs/brocc/issues
Project-URL: Source, https://github.com/SubstrateLabs/brocc
Author-email: Ben Guo <ben@substrate.run>
License-Expression: MIT
License-File: LICENSE.txt
Classifier: Development Status :: 4 - Beta
Classifier: Programming Language :: Python
Classifier: Programming Language :: Python :: 3.8
Classifier: Programming Language :: Python :: 3.9
Classifier: Programming Language :: Python :: 3.10
Classifier: Programming Language :: Python :: 3.11
Classifier: Programming Language :: Python :: 3.12
Classifier: Programming Language :: Python :: Implementation :: CPython
Classifier: Programming Language :: Python :: Implementation :: PyPy
Requires-Python: >=3.8
Requires-Dist: textual>=0.73.0
